z_rad-25.12.1.dist-info/licenses/LICENSE
zrad/__init__.py
zrad/exceptions.py
zrad/image.py
zrad/toolbox_logic.py
zrad/filtering/__init__.py
zrad/filtering/filtering.py
zrad/filtering/filtering_definitions.py
zrad/preprocessing/__init__.py
zrad/preprocessing/preprocessing.py
zrad/radiomics/__init__.py
zrad/radiomics/radiomics.py
zrad/radiomics/radiomics_definitions.py
z_rad-25.12.1.dist-info/METADATA
z_rad-25.12.1.dist-info/WHEEL
z_rad-25.12.1.dist-info/top_level.txt
z_rad-25.12.1.dist-info/RECORD
