Metadata-Version: 2.4
Name: z-rad
Version: 25.12.1
Summary: Z-Rad is a radiomic feature extraction software with GUI and API.
Author-email: Radiomics Team of Radiation Oncology Department at University Hospital Zurich <zrad@usz.ch>
License: MIT
Keywords: radiomics,feature-extraction,python,GUI,API
Requires-Python: >=3.10
License-File: LICENSE
Requires-Dist: pydicom>=3.0.0
Requires-Dist: pyqt5>=5.15.11
Requires-Dist: numpy>=2.1.1
Requires-Dist: simpleitk>=2.4.0
Requires-Dist: scipy>=1.14.1
Requires-Dist: pywavelets>=1.7.0
Requires-Dist: scikit-image>=0.24.0
Requires-Dist: opencv-python-headless>=4.10.0.84
Requires-Dist: joblib>=1.4.2
Dynamic: license-file
